{
	"rows": [
		{
			"c": [
				{
					"v": "V1"
				},
				{
					"v": "V2"
				},
				{
					"v": 0.03211422
				}
			]
		},
		{
			"c": [
				{
					"v": "V1"
				},
				{
					"v": "V3"
				},
				{
					"v": 0.02032729
				}
			]
		},
		{
			"c": [
				{
					"v": "V1"
				},
				{
					"v": "V7"
				},
				{
					"v": 0.02563341
				}
			]
		},
		{
			"c": [
				{
					"v": "V1"
				},
				{
					"v": "V8"
				},
				{
					"v": 0.05557678
				}
			]
		},
		{
			"c": [
				{
					"v": "V1"
				},
				{
					"v": "V9"
				},
				{
					"v": 0.0796134
				}
			]
		},
		{
			"c": [
				{
					"v": "V1"
				},
				{
					"v": "V10"
				},
				{
					"v": 0.2351325
				}
			]
		},
		{
			"c": [
				{
					"v": "V1"
				},
				{
					"v": "V11"
				},
				{
					"v": 0.1105089
				}
			]
		},
		{
			"c": [
				{
					"v": "V1"
				},
				{
					"v": "V12"
				},
				{
					"v": 0.02956611
				}
			]
		},
		{
			"c": [
				{
					"v": "V1"
				},
				{
					"v": "V13"
				},
				{
					"v": 0.1183971
				}
			]
		},
		{
			"c": [
				{
					"v": "V1"
				},
				{
					"v": "V14"
				},
				{
					"v": 0.1723577
				}
			]
		},
		{
			"c": [
				{
					"v": "V1"
				},
				{
					"v": "V15"
				},
				{
					"v": 0.08781203
				}
			]
		},
		{
			"c": [
				{
					"v": "V1"
				},
				{
					"v": "V16"
				},
				{
					"v": 0.155219
				}
			]
		},
		{
			"c": [
				{
					"v": "V17"
				},
				{
					"v": "V18"
				},
				{
					"v": 0.02645553
				}
			]
		},
		{
			"c": [
				{
					"v": "V17"
				},
				{
					"v": "V19"
				},
				{
					"v": 0.1604256
				}
			]
		},
		{
			"c": [
				{
					"v": "V17"
				},
				{
					"v": "V20"
				},
				{
					"v": 0.1301667
				}
			]
		},
		{
			"c": [
				{
					"v": "V17"
				},
				{
					"v": "V21"
				},
				{
					"v": 0.1798196
				}
			]
		},
		{
			"c": [
				{
					"v": "V17"
				},
				{
					"v": "V22"
				},
				{
					"v": 0.03015139
				}
			]
		},
		{
			"c": [
				{
					"v": "V17"
				},
				{
					"v": "V23"
				},
				{
					"v": 0.05666878
				}
			]
		},
		{
			"c": [
				{
					"v": "V17"
				},
				{
					"v": "V26"
				},
				{
					"v": 0.03620756
				}
			]
		},
		{
			"c": [
				{
					"v": "V17"
				},
				{
					"v": "V27"
				},
				{
					"v": 0.08915745
				}
			]
		},
		{
			"c": [
				{
					"v": "V17"
				},
				{
					"v": "V29"
				},
				{
					"v": 0.1293256
				}
			]
		},
		{
			"c": [
				{
					"v": "V17"
				},
				{
					"v": "V30"
				},
				{
					"v": 0.001329987
				}
			]
		},
		{
			"c": [
				{
					"v": "V17"
				},
				{
					"v": "V31"
				},
				{
					"v": 0.0326639
				}
			]
		},
		{
			"c": [
				{
					"v": "V17"
				},
				{
					"v": "V33"
				},
				{
					"v": 0.04170355
				}
			]
		},
		{
			"c": [
				{
					"v": "V34"
				},
				{
					"v": "V35"
				},
				{
					"v": 0.04604915
				}
			]
		},
		{
			"c": [
				{
					"v": "V34"
				},
				{
					"v": "V36"
				},
				{
					"v": 0.2416393
				}
			]
		},
		{
			"c": [
				{
					"v": "V34"
				},
				{
					"v": "V37"
				},
				{
					"v": 0.06912926
				}
			]
		},
		{
			"c": [
				{
					"v": "V34"
				},
				{
					"v": "V38"
				},
				{
					"v": 0.0857422
				}
			]
		},
		{
			"c": [
				{
					"v": "V34"
				},
				{
					"v": "V39"
				},
				{
					"v": 0.1189221
				}
			]
		},
		{
			"c": [
				{
					"v": "V34"
				},
				{
					"v": "V40"
				},
				{
					"v": 0.05802096
				}
			]
		},
		{
			"c": [
				{
					"v": "V34"
				},
				{
					"v": "V42"
				},
				{
					"v": 0.1059339
				}
			]
		},
		{
			"c": [
				{
					"v": "V34"
				},
				{
					"v": "V43"
				},
				{
					"v": 0.1851804
				}
			]
		},
		{
			"c": [
				{
					"v": "V34"
				},
				{
					"v": "V44"
				},
				{
					"v": 0.1328075
				}
			]
		},
		{
			"c": [
				{
					"v": "V34"
				},
				{
					"v": "V45"
				},
				{
					"v": 0.1313469
				}
			]
		},
		{
			"c": [
				{
					"v": "V34"
				},
				{
					"v": "V46"
				},
				{
					"v": 0.06946225
				}
			]
		},
		{
			"c": [
				{
					"v": "V34"
				},
				{
					"v": "V47"
				},
				{
					"v": 0.09878522
				}
			]
		},
		{
			"c": [
				{
					"v": "V34"
				},
				{
					"v": "V48"
				},
				{
					"v": 0.08800192
				}
			]
		},
		{
			"c": [
				{
					"v": "V34"
				},
				{
					"v": "V49"
				},
				{
					"v": 0.2135653
				}
			]
		},
		{
			"c": [
				{
					"v": "V34"
				},
				{
					"v": "V50"
				},
				{
					"v": 0.1439247
				}
			]
		}
	],
	"cols": [
		{
			"type": "string",
			"id": "A",
			"label": "Node1"
		},
		{
			"type": "string",
			"id": "B",
			"label": "Node2"
		},
		{
			"type": "number",
			"id": "C",
			"label": "Partial Correlation"
		}
	]
}